termplayer/__init__.py
termplayer/__main__.py
termplayer-0.0.1.dist-info/LICENSE
termplayer-0.0.1.dist-info/METADATA
termplayer-0.0.1.dist-info/WHEEL
termplayer-0.0.1.dist-info/entry_points.txt
termplayer-0.0.1.dist-info/top_level.txt
termplayer-0.0.1.dist-info/RECORD
