Metadata-Version: 2.1
Name: termplayer
Version: 0.0.1
Summary: A python program to help you play youtube playlists on your terminal
Home-page: UNKNOWN
Author: NeoClear
Author-email: neoclear@outlook.com
License: UNKNOWN
Platform: UNKNOWN
Requires-Python: >=3.6
License-File: LICENSE
